lightphe/__init__.py
lightphe/commons/__init__.py
lightphe/commons/logger.py
lightphe/commons/phe_utils.py
lightphe/cryptosystems/Benaloh.py
lightphe/cryptosystems/DamgardJurik.py
lightphe/cryptosystems/ElGamal.py
lightphe/cryptosystems/EllipticCurveElGamal.py
lightphe/cryptosystems/GoldwasserMicali.py
lightphe/cryptosystems/NaccacheStern.py
lightphe/cryptosystems/OkamotoUchiyama.py
lightphe/cryptosystems/Paillier.py
lightphe/cryptosystems/RSA.py
lightphe/cryptosystems/__init__.py
lightphe/models/Algorithm.py
lightphe/models/Ciphertext.py
lightphe/models/Homomorphic.py
lightphe/models/Tensor.py
lightphe/models/__init__.py
lightphe-0.0.20.data/data/README.md
lightphe-0.0.20.data/data/requirements.txt
tests/__init__.py
tests/test_benaloh.py
tests/test_ciphertexts.py
tests/test_cloud.py
tests/test_damgard.py
tests/test_elgamal.py
tests/test_ellipticcurveelgamal.py
tests/test_exporting_keys.py
tests/test_goldwasser.py
tests/test_keys.py
tests/test_large_keys.py
tests/test_naccache.py
tests/test_okamoto.py
tests/test_paillier.py
tests/test_rsa.py
tests/test_salary.py
tests/test_tensors.py
lightphe-0.0.20.dist-info/LICENSE
lightphe-0.0.20.dist-info/METADATA
lightphe-0.0.20.dist-info/WHEEL
lightphe-0.0.20.dist-info/top_level.txt
lightphe-0.0.20.dist-info/RECORD
