Metadata-Version: 2.1
Name: lightphe
Version: 0.0.20
Summary: A Lightweight Partially Homomorphic Encryption Library for Python
Home-page: https://github.com/serengil/LightPHE
Author: Sefik Ilkin Serengil
Author-email: serengil@gmail.com
License: UNKNOWN
Platform: UNKNOWN
Classifier: Programming Language :: Python :: 3
Classifier: License :: OSI Approved :: MIT License
Classifier: Operating System :: OS Independent
Requires-Python: >=3.5.5
License-File: LICENSE
